[{"@type":"Modols.Account.Account$MiniAccount","@val":{"accountId":0,"personalInformationId":123,"credit":66.0,"statusTag":"Manager"}},{"@type":"Modols.Account.Account$MiniAccount","@val":{"accountId":1,"personalInformationId":1223,"credit":66.0,"statusTag":"Seller"}},{"@type":"Modols.Account.Account$MiniAccount","@val":{"accountId":2,"personalInformationId":23,"credit":66.0,"statusTag":"Buyer"}},{"@type":"Modols.Account.Account$MiniAccount","@val":{"accountId":3,"personalInformationId":1223,"credit":66.0,"statusTag":"Buyer"}},{"@type":"Modols.Account.Account$MiniAccount","@val":{"accountId":4,"personalInformationId":1223,"credit":66.0,"statusTag":"Manager"}},{"@type":"Modols.Account.Account$MiniAccount","@val":{"accountId":5,"personalInformationId":1224543,"credit":66.0,"statusTag":"Manager"}},{"@type":"Modols.Account.Account$MiniAccount","@val":{"accountId":6,"personalInformationId":3,"credit":66.0,"statusTag":"Seller"}},{"@type":"Modols.Account.Account$MiniAccount","@val":{"accountId":7,"personalInformationId":22,"credit":66.0,"statusTag":"Buyer"}}]